<?xml version="1.0" encoding="UTF-8" standalone="yes"?>
<contentHaul xmlns:a="http://www.appian.com/ae/types/2009">
    <versionUuid>_a-0000e5c3-a65f-8000-5268-1bef901bef90_759793</versionUuid>
    <rule>
        <name>EAP_SetValueForProcessParamConfig</name>
        <uuid>_a-0000e5c3-a65f-8000-5268-1bef901bef90_759726</uuid>
        <description>Holds Set Value  For EAP_T_ProcessParamConfig.</description>
        <parentUuid>_a-0000e4c3-7a1b-8000-524f-1bef901bef90_6574</parentUuid>
        <visibility>
            <advertise>false</advertise>
            <hierarchy>true</hierarchy>
            <indexable>true</indexable>
            <quota>false</quota>
            <searchable>true</searchable>
            <system>false</system>
            <unlogged>false</unlogged>
        </visibility>
        <definition>if(
  #"_a-0000e4b2-6487-8000-2b63-01ef9001ef90_3233095"(
    ri!processParamConfig
  ),
  null,
  #"SYSTEM_SYSRULES_forEach"(
    items: ri!processParamConfig,
    expression: 'type!{urn:com:appian:types:eap}EAP_T_ProcessParamConfig'(
      process_param_id: if(
        #"_a-0000e4b2-6487-8000-2b63-01ef9001ef90_3233095"(
          ri!processParamId
        ),
        ri!processParamConfig[fv!index].process_param_id,
        ri!processParamId
      ),
      process_id: if(
        #"_a-0000e4b2-6487-8000-2b63-01ef9001ef90_3233095"(
          ri!processId
        ),
        ri!processParamConfig[fv!index].process_id,
        ri!processId
      ),
      run_config_id: if(
        #"_a-0000e4b2-6487-8000-2b63-01ef9001ef90_3233095"(
          ri!runConfigId
        ),
        ri!processParamConfig[fv!index].run_config_id,
        ri!runConfigId
      ),
      param_name: if(
        #"_a-0000e4b2-6487-8000-2b63-01ef9001ef90_3233095"(
          ri!paramName
        ),
        ri!processParamConfig[fv!index].param_name,
        ri!paramName
      ),
      param_display_name: if(
        #"_a-0000e4b2-6487-8000-2b63-01ef9001ef90_3233095"(
          ri!paramDisplayName
        ),
        ri!processParamConfig[fv!index].param_display_name,
        ri!paramDisplayName
      ),
      param_type: if(
        #"_a-0000e4b2-6487-8000-2b63-01ef9001ef90_3233095"(
          ri!paramType
        ),
        ri!processParamConfig[fv!index].param_type,
        ri!paramType
      ),
      param_desc: if(
        #"_a-0000e4b2-6487-8000-2b63-01ef9001ef90_3233095"(
          ri!paramDesc
        ),
        ri!processParamConfig[fv!index].param_desc,
        ri!paramDesc
      ),
      active: if(
        #"_a-0000e4b2-6487-8000-2b63-01ef9001ef90_3233095"(
          ri!active
        ),
        ri!processParamConfig[fv!index].active,
        ri!active
      ),
      created_by: if(
        #"_a-0000e4b2-6487-8000-2b63-01ef9001ef90_3233095"(
          ri!createdBy
        ),
        ri!processParamConfig[fv!index].created_by,
        ri!createdBy
      ),
      created_on: if(
        #"_a-0000e4b2-6487-8000-2b63-01ef9001ef90_3233095"(
          ri!createdOn
        ),
        ri!processParamConfig[fv!index].created_on,
        ri!createdOn
      ),
      modified_by: if(
        #"_a-0000e4b2-6487-8000-2b63-01ef9001ef90_3233095"(
          ri!modifiedBy
        ),
        ri!processParamConfig[fv!index].modified_by,
        ri!modifiedBy
      ),
      modified_on: if(
        #"_a-0000e4b2-6487-8000-2b63-01ef9001ef90_3233095"(
          ri!modifiedOn
        ),
        ri!processParamConfig[fv!index].modified_on,
        ri!modifiedOn
      )
    )
  )
)</definition>
        <namedTypedValue>
            <name>processParamId</name>
            <type>
                <name>Integer?list</name>
                <namespace>http://www.appian.com/ae/types/2009</namespace>
            </type>
        </namedTypedValue>
        <namedTypedValue>
            <name>processId</name>
            <type>
                <name>Integer?list</name>
                <namespace>http://www.appian.com/ae/types/2009</namespace>
            </type>
        </namedTypedValue>
        <namedTypedValue>
            <name>runConfigId</name>
            <type>
                <name>Integer?list</name>
                <namespace>http://www.appian.com/ae/types/2009</namespace>
            </type>
        </namedTypedValue>
        <namedTypedValue>
            <name>paramName</name>
            <type>
                <name>Text?list</name>
                <namespace>http://www.appian.com/ae/types/2009</namespace>
            </type>
        </namedTypedValue>
        <namedTypedValue>
            <name>paramDisplayName</name>
            <type>
                <name>Text?list</name>
                <namespace>http://www.appian.com/ae/types/2009</namespace>
            </type>
        </namedTypedValue>
        <namedTypedValue>
            <name>paramType</name>
            <type>
                <name>Text?list</name>
                <namespace>http://www.appian.com/ae/types/2009</namespace>
            </type>
        </namedTypedValue>
        <namedTypedValue>
            <name>paramDesc</name>
            <type>
                <name>Text?list</name>
                <namespace>http://www.appian.com/ae/types/2009</namespace>
            </type>
        </namedTypedValue>
        <namedTypedValue>
            <name>active</name>
            <type>
                <name>Integer?list</name>
                <namespace>http://www.appian.com/ae/types/2009</namespace>
            </type>
        </namedTypedValue>
        <namedTypedValue>
            <name>createdBy</name>
            <type>
                <name>Text?list</name>
                <namespace>http://www.appian.com/ae/types/2009</namespace>
            </type>
        </namedTypedValue>
        <namedTypedValue>
            <name>createdOn</name>
            <type>
                <name>dateTime</name>
                <namespace>http://www.w3.org/2001/XMLSchema</namespace>
            </type>
        </namedTypedValue>
        <namedTypedValue>
            <name>modifiedBy</name>
            <type>
                <name>string</name>
                <namespace>http://www.w3.org/2001/XMLSchema</namespace>
            </type>
            <value/>
        </namedTypedValue>
        <namedTypedValue>
            <name>modifiedOn</name>
            <type>
                <name>dateTime</name>
                <namespace>http://www.w3.org/2001/XMLSchema</namespace>
            </type>
        </namedTypedValue>
        <namedTypedValue>
            <name>processParamConfig</name>
            <type>
                <name>EAP_T_ProcessParamConfig?list</name>
                <namespace>urn:com:appian:types:eap</namespace>
            </type>
        </namedTypedValue>
        <preferredEditor>legacy</preferredEditor>
        <offlineEnabled>false</offlineEnabled>
    </rule>
    <roleMap public="true">
        <role inherit="true" allowForAll="false" name="readers">
            <users/>
            <groups/>
        </role>
        <role inherit="true" allowForAll="false" name="authors">
            <users/>
            <groups/>
        </role>
        <role inherit="true" allowForAll="false" name="administrators">
            <users/>
            <groups/>
        </role>
        <role inherit="false" allowForAll="false" name="denyReaders">
            <users/>
            <groups/>
        </role>
        <role inherit="false" allowForAll="false" name="denyAuthors">
            <users/>
            <groups/>
        </role>
        <role inherit="false" allowForAll="false" name="denyAdministrators">
            <users/>
            <groups/>
        </role>
    </roleMap>
    <history>
        <historyInfo versionUuid="_a-0000e5c3-a65f-8000-5268-1bef901bef90_759793"/>
    </history>
</contentHaul>
